odoo/addons/project_timeline_task_dependency/README.rst
odoo/addons/project_timeline_task_dependency/__init__.py
odoo/addons/project_timeline_task_dependency/__manifest__.py
odoo/addons/project_timeline_task_dependency/i18n/de.po
odoo/addons/project_timeline_task_dependency/i18n/es.po
odoo/addons/project_timeline_task_dependency/i18n/it.po
odoo/addons/project_timeline_task_dependency/i18n/project_timeline_task_dependency.pot
odoo/addons/project_timeline_task_dependency/readme/CONTRIBUTORS.rst
odoo/addons/project_timeline_task_dependency/readme/DESCRIPTION.rst
odoo/addons/project_timeline_task_dependency/static/description/icon.png
odoo/addons/project_timeline_task_dependency/static/description/index.html
odoo/addons/project_timeline_task_dependency/static/description/screenshot.png
odoo/addons/project_timeline_task_dependency/views/project_task_view.xml
odoo14_addon_project_timeline_task_dependency-14.0.1.0.1.dev6.dist-info/METADATA
odoo14_addon_project_timeline_task_dependency-14.0.1.0.1.dev6.dist-info/WHEEL
odoo14_addon_project_timeline_task_dependency-14.0.1.0.1.dev6.dist-info/top_level.txt
odoo14_addon_project_timeline_task_dependency-14.0.1.0.1.dev6.dist-info/RECORD
